sigma/backends/sentinelone_pq/__init__.py
sigma/backends/sentinelone_pq/sentinelone_pq.py
sigma/pipelines/sentinelone_pq/__init__.py
sigma/pipelines/sentinelone_pq/sentinelone_pq.py
pysigma_backend_sentinelone_pq-0.1.5.dist-info/LICENSE
pysigma_backend_sentinelone_pq-0.1.5.dist-info/METADATA
pysigma_backend_sentinelone_pq-0.1.5.dist-info/WHEEL
pysigma_backend_sentinelone_pq-0.1.5.dist-info/RECORD
