Metadata-Version: 2.1
Name: pySigma-backend-sentinelone-pq
Version: 0.1.5
Summary: pySigma SentinelOne PowerQuery backend
Home-page: https://github.com/7RedViolin/pySigma-backend-sentinelone-pq
License: MIT
Author: Cori Smith
Author-email: cs2718281@gmail.com
Requires-Python: >=3.8,<4.0
Classifier: License :: OSI Approved :: MIT License
Classifier: Programming Language :: Python :: 3
Classifier: Programming Language :: Python :: 3.8
Classifier: Programming Language :: Python :: 3.9
Classifier: Programming Language :: Python :: 3.10
Classifier: Programming Language :: Python :: 3.11
Classifier: Programming Language :: Python :: 3.12
Classifier: Programming Language :: Python :: 3.13
Requires-Dist: pysigma (>=0.9.5)
Project-URL: Repository, https://github.com/7RedViolin/pySigma-backend-sentinelone-pq
